[
  {
    "name": "Sofa",
    "price": 599.99,
    "category": "Living Room",
    "description": "A comfortable and stylish sofa, perfect for relaxing in your living room.",
    "image": "https://www.mydomaine.com/thmb/JLHjKxDAKNjkoTIvyDRxHhPIwmI=/4500x0/filters:no_upscale():strip_icc()/770_SantaYnez_FamilyRoom_011-82636c6ea1df487eb70fa8ed313a6369.jpg",
    "isDeleted": false
  },
  {
    "name": "Dining Table",
    "price": 349.99,
    "category": "Dining Room",
    "description": "A spacious dining table that can seat up to 6 people, made from solid wood.",
    "image": " https://www.furniturechoice.co.uk/p/l/DS10001650/DS10001650.jpg",
    "isDeleted": false
  },
  {
    "name": "Office Chair",
    "price": 129.99,
    "category": "Office Furniture",
    "description": "An ergonomic office chair that provides comfort during long working hours.",
    "image": "https://i.ibb.co.com/R7kLCYj/White-Ergonomic-Executive-Office-Chair.jpg",
    "isDeleted": false
  },
  {
    "name": "Bookshelf",
    "price": 199.99,
    "category": "Living Room",
    "description": "A stylish bookshelf that offers ample space for books and decor.",
    "image": "https://mobileimages.lowes.com/productimages/5b02e572-71ba-40ac-b204-2e028c42d98d/11162920.jpg?size=pdhism",
    "isDeleted": false
  },
  {
    "name": "Coffee Table",
    "price": 149.99,
    "category": "Living Room",
    "description": "A modern coffee table that complements any living room decor.",
    "image": "https://furniture123.co.uk/Images/TIFF002_1_Supersize.jpg?v=13",
    "isDeleted": false
  },
  {
    "name": "Bed Frame",
    "price": 399.99,
    "category": "Bedroom",
    "description": "A sturdy bed frame designed for durability and comfort.",
    "image": " https://onestopfurnitureonline.co.uk/wp-content/uploads/2018/01/white-bed-in-a-box.jpg",
    "isDeleted": false
  },
  {
    "name": "Nightstand",
    "price": 89.99,
    "category": "Bedroom",
    "description": "A simple yet elegant nightstand with a drawer for storage.",
    "image": " https://ak1.ostkcdn.com/images/products/2202042/L10468275.jpg",
    "isDeleted": false
  },
  {
    "name": "Dining Chairs",
    "price": 79.99,
    "category": "Dining Room",
    "description": "Set of 4 dining chairs with a modern design, perfect for any dining table.",
    "image": "https://images-na.ssl-images-amazon.com/images/I/71gzPEDdepL.jpg",
    "isDeleted": false
  },
  {
    "name": "Storage Ottoman",
    "price": 149.99,
    "category": "Living Room",
    "description": "A versatile storage ottoman that can serve as a seat or a footrest.",
    "image": "https://www.royhomedesign.com/wp-content/uploads/2017/06/white-leather-ottoman-coffee-table-23.jpg",
    "isDeleted": false
  },
  {
    "name": "Wardrobe",
    "price": 499.99,
    "category": "Bedroom",
    "description": "A spacious wardrobe with multiple compartments for all your clothing needs.",
    "image": "https://assets.telkitchens.co.uk/srcane/uploads/2021/07/09100400/WHITE-WARDROBE-IDEAS-5-768x521.jpg",
    "isDeleted": false
  }
]
